{
  "required": true,
  "minVersion": "0.8",
  "package": "io.ib67.sfcraft.mixin",
  "compatibilityLevel": "JAVA_21",
  "mixins": [
    "common.bridge.EntityBridge",
    "common.bridge.ItemBridge",
    "common.bridge.ServerPlayerBridge",
    "common.bridge.ServerWorldBridge"
  ],
  "client": [
  ],
  "server": [
    "common.EntityMixin",
    "common.MobEntityMixin",
    "common.PlayerEntityMixin",
    "server.AbstractFurnaceBlockMixin",
    "server.LegacyQueryHandlerMixin",
    "server.MinecraftServerMixin",
    "server.ServerHandshakeNetworkHandlerMixin",
    "server.ServerLoginNetworkHandlerMixin",
    "server.ServerPlayerEntityMixin",
    "server.ServerPlayNetworkHandlerMixin",
    "server.ServerWorldMixin",
    "server.SleepManagerMixin",
    "server.fixes.EndermanEntityMixin",
    "server.fixes.ProjectileEntityMixin",
    "server.hack.EntitySpawnS2CPacketMixin",
    "server.hack.HoverEntityContentMixin",
    "server.hack.RegistryHandlerMixin",
    "server.item.ItemMixin",
    "server.item.ItemStackMixin",
    "server.item.PlayerEntityMixin",
    "server.optimize.LivingEntityMixin",
    "server.subserver.EntityMixin",
    "server.subserver.PlayerListS2CPacket$EntryMixin",
    "server.subserver.PlayerManagerMixin",
    "server.subserver.PlayerSaveHandlerMixin",
    "server.subserver.ServerLoginNetworkHandlerMixin",
    "server.subserver.ServerPlayerEntityMixin",
    "server.subserver.WorldMixin",
    "server.subserver.command.GameRuleCommandMixin"
  ],
  "injectors": {
    "defaultRequire": 1
  }
}
